project_6/parallel2serial/src/parallel2serial.sv
module parallel2serial #(
  DATA_WIDTH = 4
) (
  input logic clk,
  input logic reset,
  input logic [DATA_WIDTH-1:0] parin, //parallel input
  input logic load, //load the parallel input
  output logic completed, //notifies end of serialization
  output logic serout //serial output
);

  //buffer to hold parallel input value when load is set to 1
  logic [DATA_WIDTH-1:0] buffered_parin;
  //counter to count bits serially output
  logic [$clog2(DATA_WIDTH)-1:0] counter;

  always_ff @(posedge clk) begin
    if (reset) begin
      serout <= 0;
      counter <= 0;
      completed <= 1'b0;
    end else if (load) begin
      buffered_parin <= parin;
      counter <= 0;
      serout <= 0;
      completed <= 1'b0;
    end else begin
      serout <= buffered_parin[DATA_WIDTH-1];

      //flag completion here
      if (counter == DATA_WIDTH - 1) begin
        completed <= 1'b1;
        //otherwise increment counter and shift the stored parallel input
      end else begin
        counter <= counter + 1;
        buffered_parin[DATA_WIDTH-1:1] <= buffered_parin[DATA_WIDTH-2:0];
      end
    end
  end

endmodule : parallel2serial

project_6/parallel2serial/src/parallel2serial_tb.sv
module parallel2serial_tb;
    // Parameters
    parameter DATA_WIDTH = 4;

    // Signals
    logic clk;
    logic reset;    
    logic [DATA_WIDTH-1:0] parin;
    logic load;
    logic completed;
    logic serout;

    // Instantiate Parallel2Serial module
    parallel2serial #(
        .DATA_WIDTH(DATA_WIDTH)
    ) dut (
        .clk(clk),
        .reset(reset),
        .parin(parin),
        .load(load),
        .completed(completed),
        .serout(serout)
    ); 

    // Clock generation
    always #5 clk = ~clk;

    // Test stimulus
    initial begin
        clk = 0;
        reset = 1;
        load = 0;
        parin = 4'b0000;

        // Wait 10 clock cycles
        #10 reset = 0;

        // Load parallel input
        #5 load = 1;
        #5 load = 0;
        #5 parin = 4'b1001;

        // Wait for completion
        #50;
        $finish;
    end

    initial begin
        $dumpfile("parallel2serial_mux.vcd");
        $dumpvars(0, parallel2serial_tb);
    end
endmodule

project_6/parallel2serial/sim/parallel2serial_mux.vcd
$date
   Mon Mar 25 15:18:20 2024
$end
$version
  2021.2
$end
$timescale
  1ps
$end
$scope module parallel2serial_tb $end
$var reg 1 ! clk $end
$var reg 1 " reset $end
$var reg 4 # parin [3:0] $end
$var reg 1 $ load $end
$var reg 1 % completed $end
$var reg 1 & serout $end
$scope module dut $end
$var wire 1 ' clk $end
$var wire 1 ( reset $end
$var wire 4 ) parin [3:0] $end
$var wire 1 * load $end
$var reg 1 % completed $end
$var reg 1 & serout $end
$var reg 4 + buffered_parin [3:0] $end
$var reg 2 , counter [1:0] $end
$upscope $end
$upscope $end
$enddefinitions $end
#0
$dumpvars
0!
1"
b0 #
0$
x%
x&
0'
1(
b0 )
0*
bx +
bx ,
$end
#5000
1!
0%
0&
1'
b0 ,
#10000
0!
0"
0'
0(
#15000
1!
1$
1'
1*
b0 +
#20000
0!
0$
0'
0*
#25000
1!
b1001 #
1'
b1001 )
b1 ,
#30000
0!
0'
#35000
1!
1'
b10 ,
#40000
0!
0'
#45000
1!
1'
b11 ,
#50000
0!
0'
#55000
1!
1%
1'
